{
  "gate_id": "gate-20260706-231712-task-20260706-231712-OS_COMPLETION_C",
  "os_version": "2.2.0",
  "contract": "dinobrain_os_v2",
  "task_id": "task-20260706-231712-OS_COMPLETION_CONDITIONS.md-",
  "request": "[OS_COMPLETION_CONDITIONS.md] 에 맞게 개선 사항 정리 후 개선. Focus this pass on turning completion-condition gaps into concrete verification artifacts and code improvements without claiming full OS completion.",
  "generated_at": "2026-07-06T23:17:12.637Z",
  "context_pack_path": ".dino/context-packs/pack-20260706-231712-OS_COMPLETION_CONDITIONS.md-.json",
  "context_item_count": 8,
  "status": "warn",
  "fail_closed": false,
  "gates": [
    {
      "id": "finish_task_required",
      "level": "warn",
      "reason": "Every started OS task must be closed with finish_task.",
      "safe_action": "Keep the task visible as active/pending until finish_task writes a trace."
    }
  ],
  "effective_sensitivity": "normal",
  "reported_sensitivity": "normal",
  "detected_sensitivity": "normal",
  "sensitivity_hits": []
}
