{
  "gate_id": "gate-20260705-075637-task-20260705-075637-Assess-whether-",
  "os_version": "2.0.1",
  "contract": "dinobrain_os_v2",
  "task_id": "task-20260705-075637-Assess-whether-DinoBrain-s-c",
  "request": "Assess whether DinoBrain's current architecture can become or already is a compounding knowledge OS tailored to the user's preferences and history under sustained use, and define the practical criteria and next engineering priorities.",
  "generated_at": "2026-07-05T07:56:37.610Z",
  "context_pack_path": ".dino/context-packs/pack-20260705-075637-Assess-whether-DinoBrain-s-c.json",
  "context_item_count": 6,
  "status": "warn",
  "fail_closed": false,
  "gates": [
    {
      "id": "finish_task_required",
      "level": "warn",
      "reason": "Every started OS task must be closed with finish_task.",
      "safe_action": "Keep the task visible as active/pending until finish_task writes a trace."
    }
  ]
}
